{
  "type_description_msg": {
    "type_description": {
      "type_name": "px4_msgs/msg/ArmingCheckReply",
      "fields": [
        {
          "name": "timestamp",
          "type": {
            "type_id": 9,
            "capacity": 0,
            "string_capacity": 0,
            "nested_type_name": ""
          },
          "default_value": ""
        },
        {
          "name": "request_id",
          "type": {
            "type_id": 3,
            "capacity": 0,
            "string_capacity": 0,
            "nested_type_name": ""
          },
          "default_value": ""
        },
        {
          "name": "registration_id",
          "type": {
            "type_id": 3,
            "capacity": 0,
            "string_capacity": 0,
            "nested_type_name": ""
          },
          "default_value": ""
        },
        {
          "name": "health_component_index",
          "type": {
            "type_id": 3,
            "capacity": 0,
            "string_capacity": 0,
            "nested_type_name": ""
          },
          "default_value": ""
        },
        {
          "name": "health_component_is_present",
          "type": {
            "type_id": 15,
            "capacity": 0,
            "string_capacity": 0,
            "nested_type_name": ""
          },
          "default_value": ""
        },
        {
          "name": "health_component_warning",
          "type": {
            "type_id": 15,
            "capacity": 0,
            "string_capacity": 0,
            "nested_type_name": ""
          },
          "default_value": ""
        },
        {
          "name": "health_component_error",
          "type": {
            "type_id": 15,
            "capacity": 0,
            "string_capacity": 0,
            "nested_type_name": ""
          },
          "default_value": ""
        },
        {
          "name": "can_arm_and_run",
          "type": {
            "type_id": 15,
            "capacity": 0,
            "string_capacity": 0,
            "nested_type_name": ""
          },
          "default_value": ""
        },
        {
          "name": "num_events",
          "type": {
            "type_id": 3,
            "capacity": 0,
            "string_capacity": 0,
            "nested_type_name": ""
          },
          "default_value": ""
        },
        {
          "name": "events",
          "type": {
            "type_id": 49,
            "capacity": 5,
            "string_capacity": 0,
            "nested_type_name": "px4_msgs/msg/Event"
          },
          "default_value": ""
        },
        {
          "name": "mode_req_angular_velocity",
          "type": {
            "type_id": 15,
            "capacity": 0,
            "string_capacity": 0,
            "nested_type_name": ""
          },
          "default_value": ""
        },
        {
          "name": "mode_req_attitude",
          "type": {
            "type_id": 15,
            "capacity": 0,
            "string_capacity": 0,
            "nested_type_name": ""
          },
          "default_value": ""
        },
        {
          "name": "mode_req_local_alt",
          "type": {
            "type_id": 15,
            "capacity": 0,
            "string_capacity": 0,
            "nested_type_name": ""
          },
          "default_value": ""
        },
        {
          "name": "mode_req_local_position",
          "type": {
            "type_id": 15,
            "capacity": 0,
            "string_capacity": 0,
            "nested_type_name": ""
          },
          "default_value": ""
        },
        {
          "name": "mode_req_local_position_relaxed",
          "type": {
            "type_id": 15,
            "capacity": 0,
            "string_capacity": 0,
            "nested_type_name": ""
          },
          "default_value": ""
        },
        {
          "name": "mode_req_global_position",
          "type": {
            "type_id": 15,
            "capacity": 0,
            "string_capacity": 0,
            "nested_type_name": ""
          },
          "default_value": ""
        },
        {
          "name": "mode_req_global_position_relaxed",
          "type": {
            "type_id": 15,
            "capacity": 0,
            "string_capacity": 0,
            "nested_type_name": ""
          },
          "default_value": ""
        },
        {
          "name": "mode_req_mission",
          "type": {
            "type_id": 15,
            "capacity": 0,
            "string_capacity": 0,
            "nested_type_name": ""
          },
          "default_value": ""
        },
        {
          "name": "mode_req_home_position",
          "type": {
            "type_id": 15,
            "capacity": 0,
            "string_capacity": 0,
            "nested_type_name": ""
          },
          "default_value": ""
        },
        {
          "name": "mode_req_prevent_arming",
          "type": {
            "type_id": 15,
            "capacity": 0,
            "string_capacity": 0,
            "nested_type_name": ""
          },
          "default_value": ""
        },
        {
          "name": "mode_req_manual_control",
          "type": {
            "type_id": 15,
            "capacity": 0,
            "string_capacity": 0,
            "nested_type_name": ""
          },
          "default_value": ""
        }
      ]
    },
    "referenced_type_descriptions": [
      {
        "type_name": "px4_msgs/msg/Event",
        "fields": [
          {
            "name": "timestamp",
            "type": {
              "type_id": 9,
              "capacity": 0,
              "string_capacity": 0,
              "nested_type_name": ""
            },
            "default_value": ""
          },
          {
            "name": "id",
            "type": {
              "type_id": 7,
              "capacity": 0,
              "string_capacity": 0,
              "nested_type_name": ""
            },
            "default_value": ""
          },
          {
            "name": "event_sequence",
            "type": {
              "type_id": 5,
              "capacity": 0,
              "string_capacity": 0,
              "nested_type_name": ""
            },
            "default_value": ""
          },
          {
            "name": "arguments",
            "type": {
              "type_id": 51,
              "capacity": 25,
              "string_capacity": 0,
              "nested_type_name": ""
            },
            "default_value": ""
          },
          {
            "name": "log_levels",
            "type": {
              "type_id": 3,
              "capacity": 0,
              "string_capacity": 0,
              "nested_type_name": ""
            },
            "default_value": ""
          }
        ]
      }
    ]
  },
  "type_hashes": [
    {
      "type_name": "px4_msgs/msg/ArmingCheckReply",
      "hash_string": "RIHS01_bbab73fbc7dedd6d2e4c40d2c14ee23f8e563fdf5e82d26d843842bfa358b07c"
    },
    {
      "type_name": "px4_msgs/msg/Event",
      "hash_string": "RIHS01_4964812eb982e8d7855e07632a5b462b0beeb3a19e116913506b339eb1c876a9"
    }
  ]
}